calib3d/__init__.py
calib3d/calib.py
calib3d-1.0.1.dist-info/LICENSE
calib3d-1.0.1.dist-info/METADATA
calib3d-1.0.1.dist-info/WHEEL
calib3d-1.0.1.dist-info/top_level.txt
calib3d-1.0.1.dist-info/RECORD
