Metadata-Version: 2.1
Name: calib3d
Version: 1.0.1
Summary: Python 3D calibration and homogenous coordinates computation library
Home-page: https://github.com/ispgroupucl/calib3d
Author: Gabriel Van Zandycke
Author-email: gabriel.vanzandycke@hotmail.com
License: LGPL
Platform: UNKNOWN
Requires-Python: >=3.6
Requires-Dist: numpy
Requires-Dist: opencv-python
